dsupdater/__init__.py
dsupdater/filter_phrases.py
dsupdater/install.py
dsupdater/output_processor.py
dsupdater/privilege_helper.py
dsupdater/shell/__init__.py
dsupdater/shell/updater.sh
dsupdater/shell_helper.py
dsupdater/update_manager.py
dsupdater/updater.py
dsupdater/updaters/__init__.py
dsupdater/updaters/chezmoi.py
dsupdater/updaters/docker_compose.py
dsupdater/updaters/ds_packages.py
dsupdater/updaters/homebrew.py
dsupdater/updaters/linux/__init__.py
dsupdater/updaters/linux/apt.py
dsupdater/updaters/linux/dnf.py
dsupdater/updaters/linux/pacman.py
dsupdater/updaters/mac_app_store.py
dsupdater/updaters/macos.py
dsupdater/updaters/python_pip.py
dsupdater-0.1.6.dist-info/LICENSE
dsupdater-0.1.6.dist-info/METADATA
dsupdater-0.1.6.dist-info/WHEEL
dsupdater-0.1.6.dist-info/entry_points.txt
dsupdater-0.1.6.dist-info/RECORD
