Metadata-Version: 2.3
Name: dsupdater
Version: 0.1.6
Summary: Multi-platform system updater script
License: GPL-3.0-or-later
Author: Danny Stewart
Author-email: danny@stewart.cc
Requires-Python: >=3.12,<3.13
Classifier: License :: OSI Approved :: GNU General Public License v3 or later (GPLv3+)
Classifier: Programming Language :: Python :: 3
Classifier: Programming Language :: Python :: 3.12
Requires-Dist: dsbase (>=0.4.1,<0.5.0)
Requires-Dist: pexpect (>=4.9.0,<5.0.0)
